ait/__init__.py
ait/backend/__init__.py
ait/backend/xilinx/__init__.py
ait/backend/xilinx/driver.py
ait/backend/xilinx/info.py
ait/backend/xilinx/IPs/bsc_axiu_addrInterleaver.v
ait/backend/xilinx/IPs/bsc_axiu_axis_subset_converter.v
ait/backend/xilinx/IPs/bsc_axiu_axis_tid_demux.v
ait/backend/xilinx/IPs/bsc_axiu_dwidth_downsizer.zip
ait/backend/xilinx/IPs/bsc_axiu_hsToStreamAdapter.v
ait/backend/xilinx/IPs/bsc_axiu_hwcounter.v
ait/backend/xilinx/IPs/bsc_axiu_memory_channel_bonding_1.0.zip
ait/backend/xilinx/IPs/bsc_axiu_streamToHsAdapter.v
ait/backend/xilinx/IPs/bsc_ompif_eth_100G_controller.zip
ait/backend/xilinx/IPs/bsc_ompif_eth_100G_rx.zip
ait/backend/xilinx/IPs/bsc_ompif_message_receiver.zip
ait/backend/xilinx/IPs/bsc_ompif_message_sender.zip
ait/backend/xilinx/IPs/bsc_ompif_packet_decoder.zip
ait/backend/xilinx/IPs/bsc_ompss_adapter_instr_1.0.zip
ait/backend/xilinx/IPs/bsc_ompss_newtask_spawner_1.0.zip
ait/backend/xilinx/IPs/bsc_ompss_picos_ompss_manager_7.3.zip
ait/backend/xilinx/board/README
ait/backend/xilinx/board/alveo_u200/baseDesign.tcl
ait/backend/xilinx/board/alveo_u200/basic_info.json
ait/backend/xilinx/board/alveo_u200/procs.tcl
ait/backend/xilinx/board/alveo_u200/constraints/acc_common_floorplan.xdc
ait/backend/xilinx/board/alveo_u200/constraints/basic_constraints.xdc
ait/backend/xilinx/board/alveo_u200/constraints/clocks.xdc
ait/backend/xilinx/board/alveo_u200/constraints/cms.xdc
ait/backend/xilinx/board/alveo_u200/constraints/create_pblocks.xdc
ait/backend/xilinx/board/alveo_u200/constraints/static_board_floorplan.xdc
ait/backend/xilinx/board/alveo_u200/constraints/static_common_floorplan.xdc
ait/backend/xilinx/board/alveo_u250/baseDesign.tcl
ait/backend/xilinx/board/alveo_u250/basic_info.json
ait/backend/xilinx/board/alveo_u250/create_pblocks.xdc
ait/backend/xilinx/board/alveo_u250/constraints/acc_common_floorplan.xdc
ait/backend/xilinx/board/alveo_u250/constraints/basic_constraints.xdc
ait_bsc-7.7.2.dist-info/LICENSE
ait_bsc-7.7.2.dist-info/METADATA
ait_bsc-7.7.2.dist-info/WHEEL
ait_bsc-7.7.2.dist-info/entry_points.txt
ait_bsc-7.7.2.dist-info/top_level.txt
ait_bsc-7.7.2.dist-info/RECORD
