Metadata-Version: 2.1
Name: ait-bsc
Version: 7.7.2
Summary: AIT - Accelerator Integration Tool
Author-email: Miquel Vidal Piñol <miquel.vidal@bsc.es>, Antonio Filgueras Izquierdo <antonio.filgueras@bsc.es>, Juan Miguel de Haro Ruiz <juan.deharoruiz@bsc.es>, Jaume Bosch Pons <jaume.bosch@bsc.es>
Maintainer-email: "OmpSs@FPGA team" <ompss-at-fpga-support@bsc.es>
License: GNU Lesser General Public License v3 (LGPLv3)
Project-URL: Homepage, https://pm.bsc.es/ompss-at-fpga
Project-URL: Documentation, https://pm.bsc.es/ftp/ompss-at-fpga/doc/user-guide-git/ait-options.html
Project-URL: Source, https://github.com/bsc-pm-ompss-at-fpga/ait
Classifier: Development Status :: 5 - Production/Stable
Classifier: Environment :: Console
Classifier: Intended Audience :: Education
Classifier: Intended Audience :: Science/Research
Classifier: License :: OSI Approved :: GNU Lesser General Public License v3 (LGPLv3)
Classifier: Operating System :: POSIX
Classifier: Programming Language :: Python :: 3
Classifier: Programming Language :: Python :: 3.7
Classifier: Programming Language :: Python :: 3.8
Classifier: Programming Language :: Python :: 3.9
Classifier: Programming Language :: Python :: 3.10
Classifier: Programming Language :: Python :: 3.11
Classifier: Programming Language :: Tcl
Classifier: Topic :: Scientific/Engineering
Classifier: Topic :: Scientific/Engineering :: Electronic Design Automation (EDA)
Requires-Python: >=3.7
License-File: LICENSE
